famapy/metamodels/bdd_metamodel/__init__.py
famapy/metamodels/bdd_metamodel/models/__init__.py
famapy/metamodels/bdd_metamodel/models/bdd_model.py
famapy/metamodels/bdd_metamodel/models/utils/__init__.py
famapy/metamodels/bdd_metamodel/models/utils/txtcnf.py
famapy/metamodels/bdd_metamodel/operations/__init__.py
famapy/metamodels/bdd_metamodel/operations/bdd_feature_inclusion_probability.py
famapy/metamodels/bdd_metamodel/operations/bdd_product_distribution.py
famapy/metamodels/bdd_metamodel/operations/bdd_products.py
famapy/metamodels/bdd_metamodel/operations/bdd_products_number.py
famapy/metamodels/bdd_metamodel/operations/bdd_sampling.py
famapy/metamodels/bdd_metamodel/operations/interfaces/__init__.py
famapy/metamodels/bdd_metamodel/operations/interfaces/feature_inclusion_probability.py
famapy/metamodels/bdd_metamodel/operations/interfaces/product_distribution.py
famapy/metamodels/bdd_metamodel/transformations/__init__.py
famapy/metamodels/bdd_metamodel/transformations/bdd_writer.py
famapy/metamodels/bdd_metamodel/transformations/fm_to_bdd.py
famapy_bdd-1.0.0.dist-info/METADATA
famapy_bdd-1.0.0.dist-info/WHEEL
famapy_bdd-1.0.0.dist-info/dependency_links.txt
famapy_bdd-1.0.0.dist-info/top_level.txt
famapy_bdd-1.0.0.dist-info/RECORD
