Metadata-Version: 2.1
Name: famapy-bdd
Version: 1.0.0
Summary: bdd-plugin for the automated analysis of feature models
Home-page: https://github.com/FaMaPy/bdd_metamodel
Author: José Miguel Horcas
Author-email: jhorcas@us.es
License: UNKNOWN
Platform: UNKNOWN
Classifier: Programming Language :: Python :: 3
Classifier: License :: OSI Approved :: GNU General Public License v3 or later (GPLv3+)
Classifier: Operating System :: OS Independent
Requires-Python: >=3.9
Requires-Dist: famapy (~=1.0.0)
Requires-Dist: famapy-fm (~=1.0.0)
Requires-Dist: dd (>=0.5.6graphviz~=0.20)
Provides-Extra: dev
Requires-Dist: pytest ; extra == 'dev'
Requires-Dist: pytest-mock ; extra == 'dev'
Requires-Dist: prospector ; extra == 'dev'
Requires-Dist: mypy ; extra == 'dev'
Requires-Dist: coverage ; extra == 'dev'
